README.txt
setup.py
docs/HISTORY.txt
docs/INSTALL.txt
docs/LICENSE.GPL
docs/LICENSE.txt
xdvtheme/__init__.py
xdvtheme.sparkling.egg-info/PKG-INFO
xdvtheme.sparkling.egg-info/SOURCES.txt
xdvtheme.sparkling.egg-info/dependency_links.txt
xdvtheme.sparkling.egg-info/entry_points.txt
xdvtheme.sparkling.egg-info/namespace_packages.txt
xdvtheme.sparkling.egg-info/not-zip-safe
xdvtheme.sparkling.egg-info/paster_plugins.txt
xdvtheme.sparkling.egg-info/requires.txt
xdvtheme.sparkling.egg-info/top_level.txt
xdvtheme/sparkling/__init__.py
xdvtheme/sparkling/configure.zcml
xdvtheme/sparkling/tests.py
xdvtheme/sparkling/profiles/default/cssregistry.xml
xdvtheme/sparkling/profiles/default/metadata.xml
xdvtheme/sparkling/profiles/default/registry.xml
xdvtheme/sparkling/static/img01.jpg
xdvtheme/sparkling/static/img02.jpg
xdvtheme/sparkling/static/index.html
xdvtheme/sparkling/static/logo.png
xdvtheme/sparkling/static/rules.xml
xdvtheme/sparkling/static/style.css