Metadata-Version: 1.0
Name: xdvtheme.sparkling
Version: 1.0-beta
Summary: An xdv Theme for Plone
Home-page: http://laplone.org
Author: Michael Miller & Mike Duggan
Author-email: mmiller@laplone.org
License: GPL
Keywords: plone xdv theme skin laplone
Platform: UNKNOWN
Classifier: Framework :: Plone
Classifier: Programming Language :: Python
Classifier: Topic :: Software Development :: Libraries :: Python Modules
